setup.py
cqs_project.egg-info/PKG-INFO
cqs_project.egg-info/SOURCES.txt
cqs_project.egg-info/dependency_links.txt
cqs_project.egg-info/requires.txt
cqs_project.egg-info/top_level.txt
untils/__init__.py
untils/test_1.py
untils/test_2.py