Metadata-Version: 1.0
Name: cqs-project
Version: 1.0.3
Summary: An feature extraction algorithm
Home-page: UNKNOWN
Author: chenqingshan
Author-email: 297110271@qq.com
License: MIT Licence
Keywords: pip,SICA,featureextraction
Platform: any
